pystatdp/__init__.py
pystatdp/_hypergeom.py
pystatdp/algorithms.py
pystatdp/core.py
pystatdp/generators.py
pystatdp/hypotest.py
pystatdp/selectors.py
pystatdp-0.1.1.dist-info/LICENSE
pystatdp-0.1.1.dist-info/METADATA
pystatdp-0.1.1.dist-info/WHEEL
pystatdp-0.1.1.dist-info/entry_points.txt
pystatdp-0.1.1.dist-info/top_level.txt
pystatdp-0.1.1.dist-info/RECORD
