Metadata-Version: 2.1
Name: pystatdp
Version: 0.1.1
Summary: Counterexample Detection Using Statistical Methods for Incorrect Differential-Privacy Algorithms.
Home-page: https://github.com/openmined/PyStatDP
Author: Harkirat Singh, Patrick Hunter
License: MIT
Keywords: Differential Privacy,Hypothesis Test,Statistics
Platform: UNKNOWN
Classifier: Development Status :: 3 - Alpha
Classifier: License :: OSI Approved :: MIT License
Classifier: Programming Language :: Python :: 3
Classifier: Operating System :: OS Independent
Requires-Python: >=3.6
Requires-Dist: numpy
Requires-Dist: tqdm
Requires-Dist: numba
Requires-Dist: jsonpickle
Requires-Dist: matplotlib
Requires-Dist: sympy
Requires-Dist: coloredlogs
Provides-Extra: test
Requires-Dist: pytest-cov ; extra == 'test'
Requires-Dist: pytest ; extra == 'test'
Requires-Dist: coverage ; extra == 'test'
Requires-Dist: flaky ; extra == 'test'
Requires-Dist: scipy ; extra == 'test'
